novu/__init__.py
novu/api/__init__.py
novu/api/base.py
novu/api/blueprint.py
novu/api/change.py
novu/api/environment.py
novu/api/event.py
novu/api/execution_detail.py
novu/api/feed.py
novu/api/inbound_parse.py
novu/api/integration.py
novu/api/layout.py
novu/api/message.py
novu/api/notification.py
novu/api/notification_group.py
novu/api/notification_template.py
novu/api/organization.py
novu/api/subscriber.py
novu/api/tenant.py
novu/api/topic.py
novu/config.py
novu/constants.py
novu/dto/__init__.py
novu/dto/base.py
novu/dto/blueprint.py
novu/dto/change.py
novu/dto/environment.py
novu/dto/event.py
novu/dto/execution_detail.py
novu/dto/feed.py
novu/dto/field.py
novu/dto/integration.py
novu/dto/layout.py
novu/dto/member.py
novu/dto/message.py
novu/dto/notification.py
novu/dto/notification_group.py
novu/dto/notification_template.py
novu/dto/organization.py
novu/dto/step_filter.py
novu/dto/subscriber.py
novu/dto/tenant.py
novu/dto/topic.py
novu/enums/__init__.py
novu/enums/change.py
novu/enums/channel.py
novu/enums/event.py
novu/enums/execution.py
novu/enums/field.py
novu/enums/member.py
novu/enums/message.py
novu/enums/notification.py
novu/enums/organization.py
novu/enums/polyfill.py
novu/enums/provider.py
novu/enums/step_filter.py
novu/enums/template.py
novu/helpers.py
novu/py.typed
novu-1.14.0.dist-info/LICENSE
novu-1.14.0.dist-info/METADATA
novu-1.14.0.dist-info/WHEEL
novu-1.14.0.dist-info/RECORD
