Metadata-Version: 2.1
Name: novu
Version: 1.14.0
Summary: This project aims to provide a wrapper for the Novu API.
Home-page: https://novu-python.readthedocs.io/en/latest
License: MIT
Keywords: novu,python,sdk,api,wrapper
Author: oscar.marie-taillefer
Author-email: oscar.marie-taillefer@spikeelabs.fr
Maintainer: oscar.marie-taillefer
Maintainer-email: oscar.marie-taillefer@spikeelabs.fr
Requires-Python: >=3.8,<4.0
Classifier: Intended Audience :: Developers
Classifier: License :: OSI Approved :: MIT License
Classifier: Operating System :: MacOS
Classifier: Operating System :: Microsoft :: Windows
Classifier: Operating System :: POSIX
Classifier: Operating System :: Unix
Classifier: Programming Language :: Python :: 3
Classifier: Programming Language :: Python :: 3.8
Classifier: Programming Language :: Python :: 3.9
Classifier: Programming Language :: Python :: 3.10
Classifier: Programming Language :: Python :: 3.11
Classifier: Programming Language :: Python :: 3.12
Classifier: Programming Language :: Python :: 3 :: Only
Classifier: Topic :: Software Development
Classifier: Typing :: Typed
Requires-Dist: requests (>=2.28.2,<3.0.0)
Project-URL: Changelog, https://github.com/novuhq/novu-python/blob/main/CHANGELOG.md
Project-URL: Documentation, https://novu-python.readthedocs.io/en/latest
Project-URL: Repository, https://github.com/novuhq/novu-python
Project-URL: Tracker, https://github.com/novuhq/novu-python/issues
